nepalitokenizer.py
src/__init__.py
src/nepalitokenizer.py
src/stopwords.py
nepalitokenizer-1.8.6.0.dist-info/LICENSE.txt
nepalitokenizer-1.8.6.0.dist-info/METADATA
nepalitokenizer-1.8.6.0.dist-info/WHEEL
nepalitokenizer-1.8.6.0.dist-info/top_level.txt
nepalitokenizer-1.8.6.0.dist-info/RECORD
