Metadata-Version: 2.1
Name: nepalitokenizer
Version: 1.8.6.0
Summary: Tokenizes Nepali Text
Home-page: UNKNOWN
License: UNKNOWN
Platform: UNKNOWN
Classifier: Programming Language :: Python :: 3
Classifier: Programming Language :: Python :: 3.6
Classifier: Programming Language :: Python :: 3.7
Classifier: License :: OSI Approved :: GNU General Public License v2 or later (GPLv2+)
Classifier: Operating System :: MacOS :: MacOS X
Classifier: Operating System :: Microsoft :: Windows
Classifier: Operating System :: POSIX
Classifier: Programming Language :: Python
Provides-Extra: dev
Requires-Dist: twine (>=3.2.0) ; extra == 'dev'
